hellodipesh/__init__.py
hellodipesh/count_nulls_neg_ones.py
hellodipesh-0.5.0.dist-info/METADATA
hellodipesh-0.5.0.dist-info/WHEEL
hellodipesh-0.5.0.dist-info/top_level.txt
hellodipesh-0.5.0.dist-info/RECORD
